[
    {
        "timestamp_ms": 0,
        "timestamp_human": "00h00m00s000ms",
        "frame_index": 0,
        "file_name": "screentime-mvp-video_001_00h00m00s000ms_0.00.jpg",
        "diff_score": 0.0
    },
    {
        "timestamp_ms": 533,
        "timestamp_human": "00h00m00s533ms",
        "frame_index": 16,
        "file_name": "screentime-mvp-video_002_00h00m00s533ms_12.25.jpg",
        "diff_score": 12.25
    },
    {
        "timestamp_ms": 2133,
        "timestamp_human": "00h00m02s133ms",
        "frame_index": 64,
        "file_name": "screentime-mvp-video_003_00h00m02s133ms_5.27.jpg",
        "diff_score": 5.27
    },
    {
        "timestamp_ms": 4866,
        "timestamp_human": "00h00m04s866ms",
        "frame_index": 146,
        "file_name": "screentime-mvp-video_004_00h00m04s866ms_3.04.jpg",
        "diff_score": 3.04
    },
    {
        "timestamp_ms": 36866,
        "timestamp_human": "00h00m36s866ms",
        "frame_index": 1106,
        "file_name": "screentime-mvp-video_005_00h00m36s866ms_3.24.jpg",
        "diff_score": 3.24
    },
    {
        "timestamp_ms": 44866,
        "timestamp_human": "00h00m44s866ms",
        "frame_index": 1346,
        "file_name": "screentime-mvp-video_006_00h00m44s866ms_8.36.jpg",
        "diff_score": 8.36
    },
    {
        "timestamp_ms": 47399,
        "timestamp_human": "00h00m47s399ms",
        "frame_index": 1422,
        "file_name": "screentime-mvp-video_007_00h00m47s399ms_3.02.jpg",
        "diff_score": 3.02
    },
    {
        "timestamp_ms": 360733,
        "timestamp_human": "00h06m00s733ms",
        "frame_index": 10822,
        "file_name": "screentime-mvp-video_008_00h06m00s733ms_3.96.jpg",
        "diff_score": 3.96
    },
    {
        "timestamp_ms": 364133,
        "timestamp_human": "00h06m04s133ms",
        "frame_index": 10924,
        "file_name": "screentime-mvp-video_009_00h06m04s133ms_9.01.jpg",
        "diff_score": 9.01
    }
]